sap2000/__init__.py
sap2000/display.py
sap2000/log.py
sap2000/main.py
sap2000/materials.py
sap2000/modal.py
sap2000/model.py
sap2000/response_spectrum.py
sap2000/results.py
sap2000/routines.py
sap2000/user_interact.py
sap2000/Base/__init__.py
sap2000/Base/constants.py
sap2000/Base/tables.py
sap2000/Base/units.py
sap2000/Results/__init__.py
sap2000-0.0.1.dist-info/LICENSE
sap2000-0.0.1.dist-info/WHEEL
sap2000-0.0.1.dist-info/METADATA
sap2000-0.0.1.dist-info/RECORD
