Metadata-Version: 2.1
Name: sap2000
Version: 0.0.1
Summary: Python App to control and manipulate SAP2000 Model
Author-email: Arun Kishore <rpakishore@gmail.com>
Classifier: License :: OSI Approved :: GNU General Public License v3 or later (GPLv3+)
Requires-Dist: ipywidgets>=8.0.3
Requires-Dist: rich>=12.6.0
Requires-Dist: ipykernel>=6.15.2
Requires-Dist: typer[all]
Requires-Dist: pandas>=1.5.2
Requires-Dist: comtypes>=1.1.14
Requires-Dist: forallpeople
Requires-Dist: pytest>=7.2.0 ; extra == "test"
Requires-Dist: pytest-cov>=4.0.0 ; extra == "test"
Project-URL: Home, https://github.com/rpakishore/sap-analysis
Provides-Extra: test
